CHANGELOG.md
CONTRIBUTING.md
LICENSE
kiwi/__init__.py
kiwi/__main__.py
kiwi/assets/__init__.py
kiwi/assets/config/__init__.py
kiwi/assets/config/evaluate.yaml
kiwi/assets/config/predict.yaml
kiwi/assets/config/pretrain.yaml
kiwi/assets/config/search.yaml
kiwi/assets/config/train.yaml
kiwi/cli.py
kiwi/constants.py
kiwi/data/__init__.py
kiwi/data/batch.py
kiwi/data/datasets/__init__.py
kiwi/data/datasets/parallel_dataset.py
kiwi/data/datasets/wmt_qe_dataset.py
kiwi/data/encoders/__init__.py
kiwi/data/encoders/base.py
kiwi/data/encoders/field_encoders.py
kiwi/data/encoders/parallel_data_encoder.py
kiwi/data/encoders/wmt_qe_data_encoder.py
kiwi/data/tokenizers.py
kiwi/data/vocabulary.py
kiwi/lib/__init__.py
kiwi/lib/evaluate.py
kiwi/lib/predict.py
kiwi/lib/pretrain.py
kiwi/lib/search.py
kiwi/lib/train.py
kiwi/lib/utils.py
kiwi/loggers.py
kiwi/metrics/__init__.py
kiwi/metrics/functions.py
kiwi/metrics/metrics.py
kiwi/modules/__init__.py
kiwi/modules/common/__init__.py
kiwi/modules/common/activations.py
kiwi/modules/common/attention.py
kiwi/modules/common/distributions.py
kiwi/modules/common/feedforward.py
kiwi/modules/common/layer_norm.py
kiwi/modules/common/positional_encoding.py
kiwi/modules/common/scalar_mix.py
kiwi/modules/common/scorer.py
kiwi/modules/sentence_level_output.py
kiwi/modules/token_embeddings.py
kiwi/modules/word_level_output.py
kiwi/runner.py
kiwi/systems/__init__.py
kiwi/systems/_meta_module.py
kiwi/systems/bert.py
kiwi/systems/decoders/__init__.py
kiwi/systems/decoders/estimator.py
kiwi/systems/decoders/linear.py
kiwi/systems/decoders/nuqe.py
kiwi/systems/encoders/__init__.py
kiwi/systems/encoders/bert.py
kiwi/systems/encoders/predictor.py
kiwi/systems/encoders/quetch.py
kiwi/systems/encoders/xlm.py
kiwi/systems/encoders/xlmroberta.py
kiwi/systems/nuqe.py
kiwi/systems/outputs/__init__.py
kiwi/systems/outputs/quality_estimation.py
kiwi/systems/outputs/translation_language_model.py
kiwi/systems/predictor.py
kiwi/systems/predictor_estimator.py
openkiwi-2.1.0.dist-info/entry_points.txt
openkiwi-2.1.0.dist-info/LICENSE
openkiwi-2.1.0.dist-info/WHEEL
openkiwi-2.1.0.dist-info/METADATA
openkiwi-2.1.0.dist-info/RECORD
