Metadata-Version: 2.1
Name: openkiwi
Version: 2.1.0
Summary: Machine Translation Quality Estimation Toolkit
Home-page: https://github.com/Unbabel/OpenKiwi
License: AGPL-3.0
Keywords: OpenKiwi,Quality Estimation,Machine Translation,Unbabel
Author: AI Research, Unbabel
Author-email: openkiwi@unbabel.com
Requires-Python: >=3.7,<4.0
Classifier: Development Status :: 4 - Beta
Classifier: Environment :: Console
Classifier: Intended Audience :: Science/Research
Classifier: License :: OSI Approved :: GNU Affero General Public License v3
Classifier: Programming Language :: Python :: 3
Classifier: Programming Language :: Python :: 3.7
Classifier: Programming Language :: Python :: 3.8
Classifier: Programming Language :: Python :: 3.9
Classifier: Topic :: Scientific/Engineering :: Artificial Intelligence
Provides-Extra: mlflow
Provides-Extra: search
Requires-Dist: docopt (>=0.6.2,<0.7.0)
Requires-Dist: hydra-core (>=0.11.3,<0.12.0)
Requires-Dist: mlflow[mlflow] (>=1.11.0,<2.0.0); extra == "mlflow"
Requires-Dist: more-itertools (>=8.0.0,<9.0.0)
Requires-Dist: numpy (>=1.18,<2.0)
Requires-Dist: omegaconf (>=1.4.1,<2.0.0)
Requires-Dist: optuna[search] (>=2.2.0,<3.0.0); extra == "search"
Requires-Dist: plotly[search] (>=4.11.0,<5.0.0); extra == "search"
Requires-Dist: pydantic (>=1.5,<2.0)
Requires-Dist: pytorch-lightning (>=0.8.4,<0.9.0)
Requires-Dist: pytorch-nlp (>=0.5.0,<0.6.0)
Requires-Dist: pyyaml (>=5.1.2,<6.0.0)
Requires-Dist: scipy (>=1.2,<2.0)
Requires-Dist: sklearn[search] (>=0.0,<0.1); extra == "search"
Requires-Dist: torch (>=1.4.0,<1.7.0)
Requires-Dist: tqdm (>=4.29,<5.0)
Requires-Dist: transformers (>=3.0.2,<4.0.0)
Requires-Dist: typing-extensions (>=3.7.4,<4.0.0)
Project-URL: Documentation, https://unbabel.github.io/OpenKiwi
Project-URL: Repository, https://github.com/Unbabel/OpenKiwi
